s3pkg
