Metadata-Version: 1.0
Name: s3-obj-semver
Version: 1.1.3
Summary: 从对象存储中，按semver规则获取最大版本号
Home-page: https://newops.cn
Author: wangsir
Author-email: wanglin@dbca.cn
License: MIT
Platform: UNKNOWN
